setup.py
yw_distributions/Binomialdistribution.py
yw_distributions/Gaussiandistribution.py
yw_distributions/Generaldistribution.py
yw_distributions/__init__.py
yw_distributions.egg-info/PKG-INFO
yw_distributions.egg-info/SOURCES.txt
yw_distributions.egg-info/dependency_links.txt
yw_distributions.egg-info/not-zip-safe
yw_distributions.egg-info/top_level.txt